psu/__init__.py
psu/entry.py
psu/exceptions.py
psu/header.py
psu/psu.py
pypsu-0.1.2.data/scripts/psu
pypsu-0.1.2.dist-info/LICENSE.md
pypsu-0.1.2.dist-info/METADATA
pypsu-0.1.2.dist-info/WHEEL
pypsu-0.1.2.dist-info/top_level.txt
pypsu-0.1.2.dist-info/RECORD
