Metadata-Version: 2.1
Name: pypsu
Version: 0.1.2
Summary: Library for analyzing and creating PS2 PSU game save files
Home-page: https://github.com/McCaulay/pypsu
Author: McCaulay Hudson
Author-email: mccaulayhudson@protonmail.com
Maintainer: McCaulay Hudson
License: MIT
Keywords: ps2 gamesave psu
Platform: Unix
Platform: Windows
Classifier: Development Status :: 4 - Beta
Classifier: Environment :: Console
Classifier: Intended Audience :: Developers
Classifier: Intended Audience :: Science/Research
Classifier: License :: OSI Approved :: MIT License
Classifier: Programming Language :: Python :: 3
License-File: LICENSE.md
